inventory_manager/__init__.py
inventory_manager/exceptions.py
inventory_manager/inventory_manager.py
inventory_manager/inventory_redis_handler.py
inventory_manager/models/__init__.py
inventory_manager/models/inventory_modification_record.py
inventory_manager/models/inventory_usage_record.py
inventory_manager-0.0.9.dev0.dist-info/METADATA
inventory_manager-0.0.9.dev0.dist-info/WHEEL
inventory_manager-0.0.9.dev0.dist-info/top_level.txt
inventory_manager-0.0.9.dev0.dist-info/RECORD
